gcb_web_auth/__init__.py
gcb_web_auth/admin.py
gcb_web_auth/apps.py
gcb_web_auth/dukeds_auth.py
gcb_web_auth/exceptions.py
gcb_web_auth/groupmanager.py
gcb_web_auth/jwt_views.py
gcb_web_auth/models.py
gcb_web_auth/test_backends.py
gcb_web_auth/test_createddsendpoint.py
gcb_web_auth/test_groupmanager.py
gcb_web_auth/test_migrations.py
gcb_web_auth/tests_dukeds_auth.py
gcb_web_auth/tests_jwt_views.py
gcb_web_auth/tests_models.py
gcb_web_auth/tests_utils.py
gcb_web_auth/tests_views.py
gcb_web_auth/urls.py
gcb_web_auth/utils.py
gcb_web_auth/views.py
gcb_web_auth/backends/__init__.py
gcb_web_auth/backends/base.py
gcb_web_auth/backends/dukeds.py
gcb_web_auth/backends/oauth.py
gcb_web_auth/management/__init__.py
gcb_web_auth/management/commands/__init__.py
gcb_web_auth/management/commands/createddsendpoint.py
gcb_web_auth/management/commands/creategroupmanagerconnection.py
gcb_web_auth/migrations/0001_initial.py
gcb_web_auth/migrations/0002_auto_20170512_1521.py
gcb_web_auth/migrations/0003_groupmanagerconnection.py
gcb_web_auth/migrations/0004_auto_20180410_1609.py
gcb_web_auth/migrations/0005_auto_20181128_1453.py
gcb_web_auth/migrations/0006_auto_20181128_1456.py
gcb_web_auth/migrations/0007_auto_20181128_1551.py
gcb_web_auth/migrations/__init__.py
gcb_web_auth/templates/gcb_web_auth/home.html
gcb_web_auth/templates/gcb_web_auth/logged_out.html
gcb_web_auth/templates/gcb_web_auth/login-local.html
gcb_web_auth/templates/gcb_web_auth/login.html
gcb_web_auth/templates/gcb_web_auth/unconfigured.html
gcb_web_auth-2.0.0.dist-info/LICENSE
gcb_web_auth-2.0.0.dist-info/METADATA
gcb_web_auth-2.0.0.dist-info/WHEEL
gcb_web_auth-2.0.0.dist-info/top_level.txt
gcb_web_auth-2.0.0.dist-info/RECORD
