Metadata-Version: 2.1
Name: gcb-web-auth
Version: 2.0.0
Summary: Django app to integrate Duke OAuth for use in GCB.
Home-page: UNKNOWN
License: MIT License
Platform: UNKNOWN
License-File: LICENSE
Requires-Dist: DukeDSClient (>=3.0.0)
Requires-Dist: PyJWT (==1.5.2)
Requires-Dist: requests (>=2.20.0)
Requires-Dist: requests-oauthlib (==0.8.0)
Requires-Dist: djangorestframework-jwt (==1.11.0)
